relion2dynamo/__init__.py
relion2dynamo/_io_converter.py
relion2dynamo/_version.py
relion2dynamo/relion2dynamo.py
relion2dynamo-1.0.6.dist-info/LICENSE.txt
relion2dynamo-1.0.6.dist-info/METADATA
relion2dynamo-1.0.6.dist-info/WHEEL
relion2dynamo-1.0.6.dist-info/entry_points.txt
relion2dynamo-1.0.6.dist-info/top_level.txt
relion2dynamo-1.0.6.dist-info/RECORD
