Metadata-Version: 2.1
Name: relion2dynamo
Version: 1.0.6
Summary: Converts RELION particle star files to Dynamo tables
Author: Euan Pyle
Author-email: euanpyle@gmail.com
License: BSD 3-Clause License
Project-URL: homepage, https://github.com/EuanPyle/relion2dynamo
Project-URL: repository, https://github.com/EuanPyle/relion2dynamo
Classifier: Development Status :: 3 - Alpha
Classifier: License :: OSI Approved :: BSD License
Classifier: Programming Language :: Python :: 3
Classifier: Programming Language :: Python :: 3.6
Classifier: Programming Language :: Python :: 3.7
Classifier: Programming Language :: Python :: 3.8
Classifier: Programming Language :: Python :: 3.9
Classifier: Programming Language :: Python :: 3.10
Requires-Python: >=3.6
License-File: LICENSE.txt
Requires-Dist: click
Requires-Dist: starfile
Requires-Dist: dynamotable
Requires-Dist: eulerangles
Requires-Dist: typer
Provides-Extra: test
Requires-Dist: pytest >=6.0 ; extra == 'test'
Requires-Dist: pytest-cov ; extra == 'test'
